LICENSE.txt
MANIFEST.in
README.md
setup.cfg
setup.py
ritzfizz/__init__.py
ritzfizz.egg-info/PKG-INFO
ritzfizz.egg-info/SOURCES.txt
ritzfizz.egg-info/dependency_links.txt
ritzfizz.egg-info/top_level.txt
ritzfizz/ritzfizz-theme/breadcrumbs.html
ritzfizz/ritzfizz-theme/footer.html
ritzfizz/ritzfizz-theme/layout.html
ritzfizz/ritzfizz-theme/layout_old.html
ritzfizz/ritzfizz-theme/search.html
ritzfizz/ritzfizz-theme/searchbox.html
ritzfizz/ritzfizz-theme/theme.conf
ritzfizz/ritzfizz-theme/versions.html
ritzfizz/ritzfizz-theme/static/css/.DS_Store
ritzfizz/ritzfizz-theme/static/css/badge_only.css
ritzfizz/ritzfizz-theme/static/css/theme.css
ritzfizz/ritzfizz-theme/static/fonts/Roboto-Bold.ttf
ritzfizz/ritzfizz-theme/static/fonts/Roboto-Light.ttf
ritzfizz/ritzfizz-theme/static/fonts/Roboto-Medium.ttf
ritzfizz/ritzfizz-theme/static/fonts/Roboto-Regular.ttf
ritzfizz/ritzfizz-theme/static/fonts/RobotoSlab-Bold.ttf
ritzfizz/ritzfizz-theme/static/fonts/RobotoSlab-Light.ttf
ritzfizz/ritzfizz-theme/static/fonts/RobotoSlab-Regular.ttf
ritzfizz/ritzfizz-theme/static/fonts/fontawesome-webfont.eot
ritzfizz/ritzfizz-theme/static/fonts/fontawesome-webfont.svg
ritzfizz/ritzfizz-theme/static/fonts/fontawesome-webfont.ttf
ritzfizz/ritzfizz-theme/static/fonts/fontawesome-webfont.woff
ritzfizz/ritzfizz-theme/static/img/logo.png
ritzfizz/ritzfizz-theme/static/js/theme.js