Metadata-Version: 1.0
Name: ritzfizz
Version: 1.0
Summary: Ritzfizz Sphinx Theme by scorpionhoney.io
Home-page: http://scorpionhoney.io
Author: Adam Temple
Author-email: adam@bixly.com
License: UNKNOWN
Keywords: sphinx,theme,readthedocs,rtd,ritzfizz,xepler,scorpionhoney
Platform: UNKNOWN
